coda_mcp_server/__init__.py
coda_mcp_server/client.py
coda_mcp_server/server.py
coda_mcp_server/models/__init__.py
coda_mcp_server/models/common.py
coda_mcp_server/models/docs.py
coda_mcp_server/models/exports.py
coda_mcp_server/models/formulas.py
coda_mcp_server/models/pages.py
coda_mcp_server/models/rows.py
coda_mcp_server/models/tables.py
coda_mcp_server/tools/__init__.py
coda_mcp_server/tools/docs.py
coda_mcp_server/tools/formulas.py
coda_mcp_server/tools/pages.py
coda_mcp_server/tools/rows.py
coda_mcp_server/tools/tables.py
coda_mcp_server-1.2.1.dist-info/licenses/LICENSE
coda_mcp_server-1.2.1.dist-info/METADATA
coda_mcp_server-1.2.1.dist-info/WHEEL
coda_mcp_server-1.2.1.dist-info/entry_points.txt
coda_mcp_server-1.2.1.dist-info/top_level.txt
coda_mcp_server-1.2.1.dist-info/RECORD
