Metadata-Version: 2.4
Name: coda-mcp-server
Version: 1.2.1
Summary: A production-ready, type-safe MCP server for Coda.io with structured outputs
Author-email: Richie Caputo <rcaputo3@tjclp.com>
License: MIT License
Project-URL: Homepage, https://github.com/TJC-LP/coda-mcp-server
Project-URL: Bug Tracker, https://github.com/TJC-LP/coda-mcp-server/issues
Project-URL: Documentation, https://github.com/TJC-LP/coda-mcp-server#readme
Project-URL: Source Code, https://github.com/TJC-LP/coda-mcp-server
Keywords: coda,mcp,server,api,integration,automation
Classifier: Development Status :: 4 - Beta
Classifier: Intended Audience :: Developers
Classifier: License :: OSI Approved :: MIT License
Classifier: Programming Language :: Python :: 3
Classifier: Programming Language :: Python :: 3.10
Classifier: Programming Language :: Python :: 3.11
Classifier: Programming Language :: Python :: 3.12
Classifier: Programming Language :: Python :: 3.13
Classifier: Programming Language :: Python :: 3.14
Classifier: Topic :: Software Development :: Libraries :: Python Modules
Classifier: Topic :: Office/Business
Classifier: Topic :: Internet :: WWW/HTTP :: Dynamic Content
Requires-Python: <3.15,>=3.11
License-File: LICENSE
Requires-Dist: aiohttp<4.0.0,>=3.13.0
Requires-Dist: mcp<2.0.0,>=1.17.0
Requires-Dist: typing_extensions>=4.9.0
Dynamic: license-file
